peewee_validates.py
peewee_validates_updated-1.0.8.dist-info/LICENSE
peewee_validates_updated-1.0.8.dist-info/METADATA
peewee_validates_updated-1.0.8.dist-info/WHEEL
peewee_validates_updated-1.0.8.dist-info/top_level.txt
peewee_validates_updated-1.0.8.dist-info/RECORD
